pyqt_date_table_widget/__init__.py
pyqt_date_table_widget/dateTableWidget.py
pyqt_date_table_widget-0.0.1.dist-info/LICENSE
pyqt_date_table_widget-0.0.1.dist-info/METADATA
pyqt_date_table_widget-0.0.1.dist-info/WHEEL
pyqt_date_table_widget-0.0.1.dist-info/top_level.txt
pyqt_date_table_widget-0.0.1.dist-info/RECORD
