Metadata-Version: 2.1
Name: pyqt-date-table-widget
Version: 0.0.1
Summary: PyQt table widget for showing date
Home-page: https://github.com/yjg30737/pyqt-date-table-widget.git
Author: Jung Gyu Yoon
Author-email: yjg30737@gmail.com
License: MIT
Platform: UNKNOWN
License-File: LICENSE
Requires-Dist: PyQt5 (>=5.8)
